metamore/__init__.py
metamore/commands/__init__.py
metamore/commands/get.py
metamore/commands/remove.py
metamore/commands/transfer.py
metamore/main.py
metamore-0.1.3.dist-info/entry_points.txt
metamore-0.1.3.dist-info/LICENSE
metamore-0.1.3.dist-info/WHEEL
metamore-0.1.3.dist-info/METADATA
metamore-0.1.3.dist-info/RECORD
