Metadata-Version: 2.1
Name: metamore
Version: 0.1.3
Summary: Metamore is a command line tool that helps you manage your metadata.
Author: voukau
Requires-Python: >=3.8,<4.0
Classifier: Programming Language :: Python :: 3
Classifier: Programming Language :: Python :: 3.8
Classifier: Programming Language :: Python :: 3.9
Requires-Dist: click (>=7.1.2,<8.0.0)
Requires-Dist: piexif (>=1.1.3,<2.0.0)
